mogussort/__init__.py
mogussort/mogussort.py
mogussort-1.0.3.dist-info/METADATA
mogussort-1.0.3.dist-info/WHEEL
mogussort-1.0.3.dist-info/RECORD
