Metadata-Version: 2.1
Name: mogussort
Version: 1.0.3
Summary: 
Home-page: https://github.com/9-FS/2023-04-10-Mogussort
License: MIT
Author: 9FS
Author-email: pray4spam@googlemail.com
Requires-Python: >=3.11.0,<4.0.0
Classifier: License :: OSI Approved :: MIT License
Classifier: Programming Language :: Python :: 3
Classifier: Programming Language :: Python :: 3.11
Project-URL: Repository, https://github.com/9-FS/2023-04-10-Mogussort
